{"name":"Searching for a term","id":"search-by-keyword;searching-for-a-term","testSteps":[{"number":1,"description":"Given Sergey is researching things on the internet","duration":13843,"startTime":"2022-11-24T08:02:33.237514630Z[Etc/UTC]","result":"SUCCESS","precondition":false,"level":0,"children":[{"number":2,"description":"Sergey opens the Wikipedia home page","duration":13464,"startTime":"2022-11-24T08:02:33.613334962Z[Etc/UTC]","result":"SUCCESS","precondition":false,"level":1,"children":[{"number":3,"description":"Sergey opens the Wikipedia home page","duration":13437,"startTime":"2022-11-24T08:02:33.633865409Z[Etc/UTC]","result":"SUCCESS","precondition":false,"level":2}]}]},{"number":4,"description":"When he looks up \"Cucumber\"","duration":941,"startTime":"2022-11-24T08:02:47.081936612Z[Etc/UTC]","result":"SUCCESS","precondition":false,"level":0,"children":[{"number":5,"description":"he searches for \u0027Cucumber\u0027","duration":908,"startTime":"2022-11-24T08:02:47.104553249Z[Etc/UTC]","result":"SUCCESS","precondition":false,"level":1,"children":[{"number":6,"description":"he enters \u0027Cucumber\u0027 then hits [ENTER] into search field","duration":903,"startTime":"2022-11-24T08:02:47.107610481Z[Etc/UTC]","result":"SUCCESS","precondition":false,"level":2}]}]},{"number":7,"description":"Then he should see information about \"Cucumber\"","duration":258,"startTime":"2022-11-24T08:02:48.023747890Z[Etc/UTC]","result":"SUCCESS","precondition":false,"level":0,"children":[{"number":8,"description":"he should see article identifier with text value that is equal to: \u003c\"Cucumber\"\u003e","duration":185,"startTime":"2022-11-24T08:02:48.093841725Z[Etc/UTC]","result":"SUCCESS","precondition":false,"level":1}]}],"userStory":{"id":"search-by-keyword","storyName":"Search by keyword","displayName":"Search by keyword","path":"search/search_by_keyword.feature","type":"feature"},"featureTag":{"name":"Search/Search by keyword","type":"feature","displayName":"Search/Search by keyword"},"title":"Searching for a term","description":"","tags":[{"name":"Search/Search by keyword","type":"feature","displayName":"Search by keyword"},{"name":"Search","type":"capability","displayName":"Search"}],"startTime":"2022-11-24T08:02:33.124346466Z[Etc/UTC]","duration":15160,"projectKey":"","sessionId":"585c41d5299415ceaebcaa9d1fbfcc4a","driver":"chrome:sergey","isManualTestingUpToDate":false,"manual":false,"testSource":"Cucumber","actors":[{"name":"Sergey","can":["browse the web"]}],"result":"SUCCESS"}